Metadata-Version: 2.1
Name: deBruijnSequences
Version: 0.0.1
Summary: generate and decode binary debruin sequences of arbitrary length
Home-page: https://github.com/emteeoh/deBruijn-Sequences
Author: Richard Betel
Author-email: emteeoh@gmail.com
License: AGPL
Platform: UNKNOWN
